morphis/__init__.py
morphis/_legacy/__init__.py
morphis/_legacy/coordinates.py
morphis/_legacy/rotations.py
morphis/_legacy/smoothing.py
morphis/_legacy/vectors.py
morphis/algebra/__init__.py
morphis/algebra/patterns.py
morphis/algebra/solvers.py
morphis/algebra/specs.py
morphis/algebra/tests/__init__.py
morphis/algebra/tests/test_patterns.py
morphis/algebra/tests/test_solvers.py
morphis/algebra/tests/test_specs.py
morphis/config.py
morphis/elements/__init__.py
morphis/elements/base.py
morphis/elements/frame.py
morphis/elements/metric.py
morphis/elements/multivector.py
morphis/elements/operator.py
morphis/elements/protocols.py
morphis/elements/tensor.py
morphis/elements/tests/__init__.py
morphis/elements/tests/test_complex_blades.py
morphis/elements/tests/test_model.py
morphis/elements/tests/test_operator.py
morphis/elements/tests/test_operators.py
morphis/elements/tests/test_tensor.py
morphis/elements/vector.py
morphis/examples/__init__.py
morphis/examples/clifford.py
morphis/examples/duality.py
morphis/examples/exterior.py
morphis/examples/operators.py
morphis/examples/phasors.py
morphis/examples/rotations_3d.py
morphis/examples/rotations_4d.py
morphis/examples/transforms_pga.py
morphis/manifold/__init__.py
morphis/operations/__init__.py
morphis/operations/_helpers.py
morphis/operations/duality.py
morphis/operations/exponential.py
morphis/operations/factorization.py
morphis/operations/matrix_rep.py
morphis/operations/norms.py
morphis/operations/operator.py
morphis/operations/outermorphism.py
morphis/operations/products.py
morphis/operations/projections.py
morphis/operations/spectral.py
morphis/operations/structure.py
morphis/operations/subspaces.py
morphis/operations/tests/__init__.py
morphis/operations/tests/test_complex_operations.py
morphis/operations/tests/test_duality.py
morphis/operations/tests/test_exponential.py
morphis/operations/tests/test_matrix_rep.py
morphis/operations/tests/test_norms.py
morphis/operations/tests/test_operations.py
morphis-0.8.0.dist-info/WHEEL
morphis-0.8.0.dist-info/entry_points.txt
morphis-0.8.0.dist-info/METADATA
morphis-0.8.0.dist-info/RECORD
