Metadata-Version: 2.4
Name: morphis
Version: 0.8.0
Summary: A unified mathematical framework for geometric computation
Keywords: geometric-algebra,mathematics,visualization,multivector,pga
Author: ctl-alt-leist
Author-email: ctl-alt-leist <ctl-alt-leist@users.noreply.github.com>
License-Expression: MIT
Classifier: Development Status :: 3 - Alpha
Classifier: Intended Audience :: Science/Research
Classifier: License :: OSI Approved :: MIT License
Classifier: Programming Language :: Python :: 3.12
Classifier: Topic :: Scientific/Engineering :: Mathematics
Classifier: Topic :: Scientific/Engineering :: Visualization
Requires-Dist: imageio>=2.37.2
Requires-Dist: imageio-ffmpeg>=0.6.0
Requires-Dist: matplotlib>=3.10.8
Requires-Dist: numpy>=2.3.5
Requires-Dist: pydantic>=2.12.5
Requires-Dist: pyvista>=0.46.4
Requires-Dist: scipy>=1.16.3
Requires-Dist: tomli>=2.3.0
Requires-Dist: build ; extra == 'dev'
Requires-Dist: flake8 ; extra == 'dev'
Requires-Dist: ipython ; extra == 'dev'
Requires-Dist: pip-tools ; extra == 'dev'
Requires-Dist: pre-commit ; extra == 'dev'
Requires-Dist: pytest ; extra == 'dev'
Requires-Dist: python-lsp-server ; extra == 'dev'
Requires-Dist: ruff ; extra == 'dev'
Requires-Python: >=3.12
Project-URL: Homepage, https://github.com/ctl-alt-leist/morphis
Project-URL: Repository, https://github.com/ctl-alt-leist/morphis
Project-URL: Issues, https://github.com/ctl-alt-leist/morphis/issues
Provides-Extra: dev
